odoo/addons/res_partner_operating_unit/README.rst
odoo/addons/res_partner_operating_unit/__init__.py
odoo/addons/res_partner_operating_unit/__manifest__.py
odoo/addons/res_partner_operating_unit/i18n/pt.po
odoo/addons/res_partner_operating_unit/i18n/res_partner_operating_unit.pot
odoo/addons/res_partner_operating_unit/models/__init__.py
odoo/addons/res_partner_operating_unit/models/res_partner.py
odoo/addons/res_partner_operating_unit/models/res_users.py
odoo/addons/res_partner_operating_unit/readme/CONTRIBUTORS.rst
odoo/addons/res_partner_operating_unit/readme/CREDITS.rst
odoo/addons/res_partner_operating_unit/readme/DESCRIPTION.rst
odoo/addons/res_partner_operating_unit/readme/USAGE.rst
odoo/addons/res_partner_operating_unit/static/description/icon.png
odoo/addons/res_partner_operating_unit/static/description/index.html
odoo/addons/res_partner_operating_unit/tests/__init__.py
odoo/addons/res_partner_operating_unit/tests/test_res_partner_operating_unit.py
odoo/addons/res_partner_operating_unit/views/res_partner_view.xml
odoo12_addon_res_partner_operating_unit-12.0.1.1.1.dist-info/METADATA
odoo12_addon_res_partner_operating_unit-12.0.1.1.1.dist-info/WHEEL
odoo12_addon_res_partner_operating_unit-12.0.1.1.1.dist-info/top_level.txt
odoo12_addon_res_partner_operating_unit-12.0.1.1.1.dist-info/RECORD
